gcp_saving/__init__.py
tests/__init__.py
gcp_saving-0.0.2.dist-info/LICENSE
gcp_saving-0.0.2.dist-info/METADATA
gcp_saving-0.0.2.dist-info/WHEEL
gcp_saving-0.0.2.dist-info/top_level.txt
gcp_saving-0.0.2.dist-info/RECORD
