Metadata-Version: 2.1
Name: gcp-saving
Version: 0.0.2
Summary: GCP saving Python package
Home-page: https://gcp-saving.readthedocs.io/
Author: Alessandra Bilardi
Author-email: alessandra.bilardi@gmail.com
License: UNKNOWN
Project-URL: Source, https://github.com/bilardi/gcp-saving
Project-URL: Bug Reports, https://github.com/bilardi/gcp-saving/issues
Project-URL: Funding, https://donate.pypi.org
Platform: UNKNOWN
Classifier: Programming Language :: Python :: 3
Classifier: License :: OSI Approved :: MIT License
Classifier: Operating System :: OS Independent
Requires-Python: >=3.6
